<?xml version="1.0" encoding="utf-8"?>
<!DOCTYPE score-partwise  PUBLIC "-//Recordare//DTD MusicXML 3.0 Partwise//EN" "http://www.musicxml.org/dtds/partwise.dtd">
<score-partwise version="3.0">
  <work>
    <work-title>careless_wisper</work-title>
  </work>
  <movement-title>careless_wisper</movement-title>
  <identification>
    <creator type="composer">jazz/</creator>
    <encoding>
      <encoding-date>2019-01-20</encoding-date>
      <software>music21 v.5.3.0</software>
    </encoding>
  </identification>
  <defaults>
    <scaling>
      <millimeters>7</millimeters>
      <tenths>40</tenths>
    </scaling>
  </defaults>
  <part-list>
    <score-part id="Pb1bfa380421601c343c2da9b2f1c39b5">
      <part-name />
    </score-part>
  </part-list>
  <!--=========================== Part 1 ===========================-->
  <part id="Pb1bfa380421601c343c2da9b2f1c39b5">
    <!--========================= Measure 2 ==========================-->
    <measure number="2" width="600">
      <print new-system="no" />
      <attributes>
        <divisions>10080</divisions>
        <time>
          <beats>4</beats>
          <beat-type>4</beat-type>
        </time>
      </attributes>
      <note>
        <pitch>
          <step>E</step>
          <octave>5</octave>
        </pitch>
        <duration>5040</duration>
        <type>eighth</type>
        <stem>down</stem>
      </note>
      <note>
        <pitch>
          <step>E</step>
          <octave>5</octave>
        </pitch>
        <duration>10080</duration>
        <type>quarter</type>
        <stem>down</stem>
      </note>
      <note>
        <pitch>
          <step>D</step>
          <octave>5</octave>
        </pitch>
        <duration>5040</duration>
        <type>eighth</type>
        <stem>down</stem>
      </note>
      <note>
        <pitch>
          <step>D</step>
          <octave>5</octave>
        </pitch>
        <duration>5040</duration>
        <type>eighth</type>
        <stem>down</stem>
      </note>
      <note>
        <pitch>
          <step>C</step>
          <octave>5</octave>
        </pitch>
        <duration>10080</duration>
        <type>quarter</type>
        <stem>down</stem>
      </note>
      <note>
        <pitch>
          <step>A</step>
          <octave>4</octave>
        </pitch>
        <duration>5040</duration>
        <type>eighth</type>
        <stem>up</stem>
      </note>
    </measure>
    <!--========================= Measure 3 ==========================-->
    <measure number="3" width="628">
      <print new-system="no" />
      <forward>
        <duration>10080</duration>
      </forward>
      <note>
        <rest />
        <duration>10080</duration>
        <type>quarter</type>
      </note>
      <note>
        <rest />
        <duration>10080</duration>
        <type>quarter</type>
      </note>
      <note>
        <rest />
        <duration>5040</duration>
        <type>eighth</type>
      </note>
      <note>
        <pitch>
          <step>A</step>
          <octave>4</octave>
        </pitch>
        <duration>2520</duration>
        <type>16th</type>
        <stem>up</stem>
        <beam number="1">begin</beam>
        <beam number="2">begin</beam>
      </note>
      <note>
        <pitch>
          <step>A</step>
          <octave>4</octave>
        </pitch>
        <duration>2520</duration>
        <type>16th</type>
        <stem>up</stem>
        <beam number="1">end</beam>
        <beam number="2">end</beam>
      </note>
    </measure>
    <!--========================= Measure 4 ==========================-->
    <measure number="4" width="689">
      <print new-system="yes">
        <system-layout>
          <system-margins>
            <left-margin>2</left-margin>
            <right-margin>0</right-margin>
          </system-margins>
          <system-distance>203</system-distance>
        </system-layout>
      </print>
      <note>
        <pitch>
          <step>E</step>
          <octave>5</octave>
        </pitch>
        <duration>10080</duration>
        <type>quarter</type>
        <stem>down</stem>
      </note>
      <note>
        <pitch>
          <step>F</step>
          <octave>5</octave>
        </pitch>
        <duration>5040</duration>
        <type>eighth</type>
        <stem>down</stem>
        <beam number="1">begin</beam>
      </note>
      <note>
        <pitch>
          <step>D</step>
          <octave>5</octave>
        </pitch>
        <duration>5040</duration>
        <type>eighth</type>
        <stem>down</stem>
        <beam number="1">end</beam>
      </note>
      <note>
        <pitch>
          <step>D</step>
          <octave>5</octave>
        </pitch>
        <duration>5040</duration>
        <type>eighth</type>
        <stem>down</stem>
        <beam number="1">begin</beam>
      </note>
      <note>
        <pitch>
          <step>A</step>
          <octave>4</octave>
        </pitch>
        <duration>5040</duration>
        <type>eighth</type>
        <stem>down</stem>
        <beam number="1">continue</beam>
      </note>
      <note>
        <pitch>
          <step>C</step>
          <octave>5</octave>
        </pitch>
        <duration>5040</duration>
        <type>eighth</type>
        <stem>down</stem>
        <beam number="1">continue</beam>
      </note>
      <note>
        <pitch>
          <step>A</step>
          <octave>4</octave>
        </pitch>
        <duration>5040</duration>
        <type>eighth</type>
        <stem>down</stem>
        <beam number="1">end</beam>
      </note>
    </measure>
    <!--========================= Measure 5 ==========================-->
    <measure number="5" width="644">
      <print new-system="no" />
      <note>
        <pitch>
          <step>E</step>
          <octave>5</octave>
        </pitch>
        <duration>10080</duration>
        <type>quarter</type>
        <stem>down</stem>
      </note>
      <note>
        <pitch>
          <step>D</step>
          <octave>5</octave>
        </pitch>
        <duration>10080</duration>
        <type>quarter</type>
        <stem>down</stem>
      </note>
      <note>
        <pitch>
          <step>C</step>
          <octave>5</octave>
        </pitch>
        <duration>10080</duration>
        <type>quarter</type>
        <stem>down</stem>
      </note>
      <note>
        <pitch>
          <step>B</step>
          <octave>4</octave>
        </pitch>
        <duration>10080</duration>
        <type>quarter</type>
        <stem>up</stem>
      </note>
    </measure>
    <!--========================= Measure 6 ==========================-->
    <measure number="6" width="668">
      <print new-system="yes">
        <system-layout>
          <system-margins>
            <left-margin>0</left-margin>
            <right-margin>0</right-margin>
          </system-margins>
          <system-distance>189</system-distance>
        </system-layout>
      </print>
      <note>
        <rest />
        <duration>5040</duration>
        <type>eighth</type>
      </note>
      <note>
        <pitch>
          <step>A</step>
          <octave>4</octave>
        </pitch>
        <duration>2520</duration>
        <type>16th</type>
        <stem>up</stem>
        <beam number="1">begin</beam>
        <beam number="2">begin</beam>
      </note>
      <note>
        <pitch>
          <step>B</step>
          <octave>4</octave>
        </pitch>
        <duration>2520</duration>
        <type>16th</type>
        <stem>up</stem>
        <beam number="1">end</beam>
        <beam number="2">end</beam>
      </note>
      <note>
        <pitch>
          <step>C</step>
          <octave>5</octave>
        </pitch>
        <duration>5040</duration>
        <type>eighth</type>
        <stem>down</stem>
        <beam number="1">begin</beam>
      </note>
      <note>
        <pitch>
          <step>D</step>
          <octave>5</octave>
        </pitch>
        <duration>2520</duration>
        <type>16th</type>
        <stem>down</stem>
        <beam number="1">continue</beam>
        <beam number="2">begin</beam>
      </note>
      <note>
        <pitch>
          <step>E</step>
          <octave>5</octave>
        </pitch>
        <duration>2520</duration>
        <type>16th</type>
        <stem>down</stem>
        <beam number="1">end</beam>
        <beam number="2">end</beam>
      </note>
      <note>
        <pitch>
          <step>E</step>
          <octave>5</octave>
        </pitch>
        <duration>10080</duration>
        <type>quarter</type>
        <stem>down</stem>
      </note>
      <note>
        <rest />
        <duration>10080</duration>
        <type>quarter</type>
      </note>
    </measure>
    <!--========================= Measure 7 ==========================-->
    <measure number="7" width="667">
      <print new-system="no" />
      <note>
        <rest />
        <duration>5040</duration>
        <type>eighth</type>
      </note>
      <note>
        <pitch>
          <step>A</step>
          <octave>4</octave>
        </pitch>
        <duration>2520</duration>
        <type>16th</type>
        <stem>up</stem>
        <beam number="1">begin</beam>
        <beam number="2">begin</beam>
      </note>
      <note>
        <pitch>
          <step>B</step>
          <octave>4</octave>
        </pitch>
        <duration>2520</duration>
        <type>16th</type>
        <stem>up</stem>
        <beam number="1">end</beam>
        <beam number="2">end</beam>
      </note>
      <note>
        <pitch>
          <step>C</step>
          <octave>5</octave>
        </pitch>
        <duration>5040</duration>
        <type>eighth</type>
        <stem>down</stem>
        <beam number="1">begin</beam>
      </note>
      <note>
        <pitch>
          <step>A</step>
          <octave>4</octave>
        </pitch>
        <duration>2520</duration>
        <type>16th</type>
        <stem>down</stem>
        <beam number="1">continue</beam>
        <beam number="2">begin</beam>
      </note>
      <note>
        <pitch>
          <step>G</step>
          <octave>5</octave>
        </pitch>
        <duration>7560</duration>
        <type>eighth</type>
        <dot />
        <stem>down</stem>
        <beam number="1">end</beam>
        <beam number="2">end</beam>
      </note>
      <note>
        <pitch>
          <step>F</step>
          <octave>5</octave>
        </pitch>
        <duration>5040</duration>
        <type>eighth</type>
        <stem>down</stem>
        <beam number="1">end</beam>
      </note>
      <note>
        <rest />
        <duration>10080</duration>
        <type>quarter</type>
      </note>
    </measure>
    <!--========================= Measure 8 ==========================-->
    <measure number="8" width="501">
      <print new-system="yes">
        <system-layout>
          <system-margins>
            <left-margin>0</left-margin>
            <right-margin>0</right-margin>
          </system-margins>
          <system-distance>229</system-distance>
        </system-layout>
      </print>
      <note>
        <pitch>
          <step>E</step>
          <octave>5</octave>
        </pitch>
        <duration>5040</duration>
        <type>eighth</type>
        <stem>down</stem>
        <beam number="1">begin</beam>
      </note>
      <note>
        <pitch>
          <step>F</step>
          <octave>5</octave>
        </pitch>
        <duration>5040</duration>
        <type>eighth</type>
        <stem>down</stem>
        <beam number="1">continue</beam>
        <notations>
          <articulations>
            <strong-accent placement="below" type="up" />
          </articulations>
        </notations>
      </note>
      <note>
        <pitch>
          <step>E</step>
          <octave>5</octave>
        </pitch>
        <duration>5040</duration>
        <type>eighth</type>
        <stem>down</stem>
        <beam number="1">continue</beam>
      </note>
      <note>
        <pitch>
          <step>F</step>
          <octave>5</octave>
        </pitch>
        <duration>5040</duration>
        <type>eighth</type>
        <stem>down</stem>
        <beam number="1">end</beam>
      </note>
      <note>
        <pitch>
          <step>E</step>
          <octave>5</octave>
        </pitch>
        <duration>5040</duration>
        <type>eighth</type>
        <stem>down</stem>
        <beam number="1">begin</beam>
      </note>
      <note>
        <pitch>
          <step>F</step>
          <octave>5</octave>
        </pitch>
        <duration>2520</duration>
        <type>16th</type>
        <stem>down</stem>
        <beam number="1">continue</beam>
        <beam number="2">begin</beam>
      </note>
      <note>
        <pitch>
          <step>E</step>
          <octave>5</octave>
        </pitch>
        <duration>10080</duration>
        <type>quarter</type>
        <stem>down</stem>
        <beam number="1">end</beam>
        <beam number="2">end</beam>
      </note>
      <note>
        <pitch>
          <step>C</step>
          <octave>5</octave>
        </pitch>
        <duration>2520</duration>
        <type>16th</type>
        <stem>down</stem>
        <beam number="1">end</beam>
        <beam number="2">backward hook</beam>
      </note>
    </measure>
    <!--========================= Measure 9 ==========================-->
    <measure number="9" width="359">
      <print new-system="no" />
      <note>
        <pitch>
          <step>E</step>
          <octave>5</octave>
        </pitch>
        <duration>10080</duration>
        <type>quarter</type>
        <stem>down</stem>
      </note>
      <note>
        <pitch>
          <step>D</step>
          <octave>5</octave>
        </pitch>
        <duration>10080</duration>
        <type>quarter</type>
        <stem>down</stem>
      </note>
      <note>
        <pitch>
          <step>C</step>
          <octave>5</octave>
        </pitch>
        <duration>10080</duration>
        <type>quarter</type>
        <stem>down</stem>
      </note>
      <note>
        <pitch>
          <step>B</step>
          <octave>4</octave>
        </pitch>
        <duration>7560</duration>
        <type>eighth</type>
        <dot />
        <stem>up</stem>
        <beam number="1">begin</beam>
      </note>
      <note>
        <pitch>
          <step>A</step>
          <octave>4</octave>
        </pitch>
        <duration>2520</duration>
        <type>16th</type>
        <stem>up</stem>
        <beam number="1">end</beam>
        <beam number="2">backward hook</beam>
      </note>
    </measure>
  </part>
</score-partwise>